source/TreeModel.py
source/__init__.py
source/draw_path.py
source/tree_visualizer.py
tests/__init__.py
tests/test_TreeModel.py
tests/test_draw_path.py
tests/test_tree_visualization.py
TreeModelVis-0.1.0.dist-info/LICENSE
TreeModelVis-0.1.0.dist-info/METADATA
TreeModelVis-0.1.0.dist-info/WHEEL
TreeModelVis-0.1.0.dist-info/top_level.txt
TreeModelVis-0.1.0.dist-info/RECORD
