Metadata-Version: 2.1
Name: TreeModelVis
Version: 0.1.0
Summary: A toolkit for visualizing and customizing tree-based models.
Home-page: https://github.com/bdi2357/TreeModelVis
Author: Itay Ben Dan
Author-email: itaybd@gmail.com
License: UNKNOWN
Platform: UNKNOWN
Classifier: Development Status :: 4 - Beta
Classifier: Intended Audience :: Developers
Classifier: Intended Audience :: Science/Research
Classifier: Natural Language :: English
Classifier: Programming Language :: Python :: 3
Classifier: Programming Language :: Python :: 3.10
Classifier: License :: OSI Approved :: MIT License
Classifier: Operating System :: OS Independent
Requires-Python: >=3.6
License-File: LICENSE
Requires-Dist: graphviz (==0.20.1)
Requires-Dist: numpy (==1.26.3)
Requires-Dist: pandas (==2.2.0)
Requires-Dist: scikit-learn (==1.4.0)
